lumaCLI/__init__.py
lumaCLI/luma.py
lumaCLI/commands/__init__.py
lumaCLI/commands/config.py
lumaCLI/commands/dbt.py
lumaCLI/commands/postgres.py
lumaCLI/metadata/__init__.py
lumaCLI/metadata/models/bi.py
lumaCLI/metadata/models/database.py
lumaCLI/metadata/sources/__init__.py
lumaCLI/metadata/sources/powerbi/extract.py
lumaCLI/metadata/sources/powerbi/models.py
lumaCLI/metadata/sources/powerbi/pipeline.py
lumaCLI/metadata/sources/powerbi/transform.py
lumaCLI/metadata/sources/sap/extract.py
lumaCLI/metadata/sources/sap/pipeline.py
lumaCLI/metadata/sources/sap/transform.py
lumaCLI/models/__init__.py
lumaCLI/models/configs.py
lumaCLI/models/dbt.py
lumaCLI/utils/__init__.py
lumaCLI/utils/luma_utils.py
lumaCLI/utils/options.py
lumaCLI/utils/postgres_utils.py
lumaCLI/utils/state.py
lumacli-0.2.11.dist-info/METADATA
lumacli-0.2.11.dist-info/WHEEL
lumacli-0.2.11.dist-info/entry_points.txt
lumacli-0.2.11.dist-info/licenses/LICENSE
lumacli-0.2.11.dist-info/RECORD
